{
  "month": "Апрель 2026",
  "phone": "+7 (924) 458-88-78",
  "priest": "отец Николай",
  "services": [
    {
      "date": "04 апреля (Сб)",
      "time": "11:00",
      "title": "ЛАЗАРЕВА СУББОТА",
      "desc": "Таинство Крещения"
    },
    {
      "date": "05 апреля (Вс)",
      "time": "10:00",
      "title": "ВЕРБНОЕ ВОСКРЕСЕНЬЕ",
      "desc": "Божественная литургия. Исповедь. Причастие. Освящение вербы. В 11:00 — Беседа для готовящихся креститься."
    },
    {
      "date": "07 апреля (Вт)",
      "time": "10:00",
      "title": "БЛАГОВЕЩЕНИЕ ПРЕСВЯТОЙ БОГОРОДИЦЫ",
      "desc": "Божественная литургия. Исповедь. Причастие."
    },
    {
      "date": "11 апреля (Сб)",
      "time": "11:00",
      "title": "ВЕЛИКАЯ СУББОТА",
      "desc": "Таинство Крещения"
    },
    {
      "date": "11 - 12 апреля (Сб/Вс)",
      "time": "23:30",
      "title": "СВЕТЛОЕ ХРИСТОВО ВОСКРЕСЕНИЕ. ПАСХА",
      "desc": "Крестный ход. Божественная литургия. Причастие. Освящение куличей и яиц."
    },
    {
      "date": "21 апреля (Вт)",
      "time": "10:00",
      "title": "РАДОНИЦА",
      "desc": "Поминовение усопших. Заупокойное богослужение."
    }
  ]
}
